twitter_markov/__init__.py
twitter_markov/__main__.py
twitter_markov/checking.py
twitter_markov/twitter_markov.py
twitter_markov-0.6.0.dist-info/LICENSE
twitter_markov-0.6.0.dist-info/METADATA
twitter_markov-0.6.0.dist-info/WHEEL
twitter_markov-0.6.0.dist-info/entry_points.txt
twitter_markov-0.6.0.dist-info/pbr.json
twitter_markov-0.6.0.dist-info/top_level.txt
twitter_markov-0.6.0.dist-info/zip-safe
twitter_markov-0.6.0.dist-info/RECORD
