Metadata-Version: 2.1
Name: twitter-markov
Version: 0.6.0
Summary: Create markov chain ("_ebooks") accounts on Twitter
Home-page: https://github.com/fitnr/twitter_markov
Author: Neil Freeman
Author-email: contact@fakeisthenewreal.org
License: GPLv3
Platform: UNKNOWN
Classifier: Development Status :: 4 - Beta
Classifier: Intended Audience :: Developers
Classifier: License :: OSI Approved :: GNU General Public License v3 (GPLv3)
Classifier: Programming Language :: Python :: 3.5
Classifier: Programming Language :: Python :: 3.6
Classifier: Programming Language :: Python :: 3.7
Classifier: Programming Language :: Python :: 3.8
Classifier: Operating System :: OS Independent
Requires-Dist: twitter-bot-utils (>=0.12.0)
Requires-Dist: markovify (<0.4,>=0.2.4)
Requires-Dist: python-Levenshtein (<0.13,>=0.12.0)
Requires-Dist: wordfilter (>=0.1.8)
Requires-Dist: pyyaml (>=4.2b1)
Requires-Dist: tweepy
Requires-Dist: six
